redten
